discord/ext/flags/__init__.py
discord_ext_flags-0.0.1a0.dist-info/LICENSE
discord_ext_flags-0.0.1a0.dist-info/METADATA
discord_ext_flags-0.0.1a0.dist-info/WHEEL
discord_ext_flags-0.0.1a0.dist-info/top_level.txt
discord_ext_flags-0.0.1a0.dist-info/RECORD
